setup.cfg
setup.py
iw/__init__.py
iw.debug.egg-info/PKG-INFO
iw.debug.egg-info/SOURCES.txt
iw.debug.egg-info/dependency_links.txt
iw.debug.egg-info/entry_points.txt
iw.debug.egg-info/namespace_packages.txt
iw.debug.egg-info/not-zip-safe
iw.debug.egg-info/requires.txt
iw.debug.egg-info/top_level.txt
iw/debug/CHANGES
iw/debug/README.txt
iw/debug/__init__.py
iw/debug/config.py
iw/debug/configure.zcml
iw/debug/pdbview.py
iw/debug/version.txt
iw/debug/docs/README.txt