Metadata-Version: 1.0
Name: iw.debug
Version: 0.3
Summary: Tools to help debugging a zope based application
Home-page: https://ingeniweb.svn.sourceforge.net/svnroot/ingeniweb/iw.debug
Author: Ingeniweb
Author-email: support@ingeniweb.com
License: GPL
Keywords: debug pdb ipdb plone zope
Platform: UNKNOWN
Classifier: Framework :: Plone
Classifier: Framework :: Zope2
Classifier: Framework :: Zope3
Classifier: Programming Language :: Python
Classifier: Topic :: Software Development :: Libraries :: Python Modules
